numericalint.py
numericalint-0.0.1.dist-info/LICENSE
numericalint-0.0.1.dist-info/METADATA
numericalint-0.0.1.dist-info/WHEEL
numericalint-0.0.1.dist-info/top_level.txt
numericalint-0.0.1.dist-info/RECORD
